{
  "title": "ROS cpp py basics",
  "description": "In this environment you will initialize ROS.",
  "details": {
    "intro": {
      "text": "intro.md"
    },
    "steps": [
      {
        "title": "Install dependencies",
        "text": "step1.md"
      },
      {
        "title": "Install dependencies",
        "text": "step2.md"
      },
      {
        "title": "ROS Workspace",
        "text": "step3.md"
      }    
    ],
    "finish": {
      "text": "finish.md"
    }
  },
  "backend": {
    "imageid": "ubuntu"
  }
}
